struct_tools/__init__.py
struct_tools-0.2.7.dist-info/WHEEL
struct_tools-0.2.7.dist-info/METADATA
struct_tools-0.2.7.dist-info/RECORD
