Metadata-Version: 2.1
Name: struct-tools
Version: 0.2.7
Summary: Tools for working with dicts (and lists)
License: MIT
Keywords: dict,list
Author: patricknraanes
Author-email: patrick.n.raanes@gmail.com
Requires-Python: >=3.7,<4.0
Classifier: License :: OSI Approved :: MIT License
Classifier: Programming Language :: Python :: 3
Classifier: Programming Language :: Python :: 3.7
Classifier: Programming Language :: Python :: 3.8
Classifier: Programming Language :: Python :: 3.9
Requires-Dist: importlib-metadata (>=1.0,<2.0); python_version < "3.8"
